pplbench/__init__.py
pplbench/__main__.py
pplbench/main.py
pplbench/lib/__init__.py
pplbench/lib/model_helper.py
pplbench/lib/ppl_helper.py
pplbench/lib/reports.py
pplbench/lib/utils.py
pplbench/models/__init__.py
pplbench/models/base_model.py
pplbench/models/crowd_sourced_annotation.py
pplbench/models/logistic_regression.py
pplbench/models/n_schools.py
pplbench/models/noisy_or_topic.py
pplbench/models/robust_regression.py
pplbench/models/utils.py
pplbench/ppls/__init__.py
pplbench/ppls/base_ppl_impl.py
pplbench/ppls/base_ppl_inference.py
pplbench/ppls/jags/__init__.py
pplbench/ppls/jags/base_jags_impl.py
pplbench/ppls/jags/inference.py
pplbench/ppls/jags/logistic_regression.py
pplbench/ppls/jags/n_schools.py
pplbench/ppls/jags/noisy_or_topic.py
pplbench/ppls/jags/robust_regression.py
pplbench/ppls/numpyro/__init__.py
pplbench/ppls/numpyro/base_numpyro_impl.py
pplbench/ppls/numpyro/inference.py
pplbench/ppls/numpyro/logistic_regression.py
pplbench/ppls/pymc3/__init__.py
pplbench/ppls/pymc3/base_pymc3_impl.py
pplbench/ppls/pymc3/inference.py
pplbench/ppls/pymc3/logistic_regression.py
pplbench/ppls/pymc3/noisy_or_topic.py
pplbench/ppls/pymc3/robust_regression.py
pplbench/ppls/stan/__init__.py
pplbench/ppls/stan/base_stan_impl.py
pplbench/ppls/stan/crowd_sourced_annotation.py
pplbench/ppls/stan/inference.py
pplbench/ppls/stan/logistic_regression.py
pplbench/ppls/stan/n_schools.py
pplbench/ppls/stan/noisy_or_topic.py
pplbench/ppls/stan/robust_regression.py
pplbench-0.0.2.dist-info/LICENSE
pplbench-0.0.2.dist-info/METADATA
pplbench-0.0.2.dist-info/WHEEL
pplbench-0.0.2.dist-info/entry_points.txt
pplbench-0.0.2.dist-info/top_level.txt
pplbench-0.0.2.dist-info/RECORD
