Metadata-Version: 2.1
Name: pplbench
Version: 0.0.2
Summary: Evaluation framework for probabilistic programming languages
Home-page: UNKNOWN
Author: Facebook, Inc.
License: MIT
Project-URL: Documentation, https://pplbench.org
Project-URL: Source, https://github.com/facebookresearch/pplbench
Keywords: Probabilistic Programming Language,Bayesian Inference,Statistical Modeling,MCMC,PyTorch
Platform: UNKNOWN
Classifier: Development Status :: 3 - Alpha
Classifier: Programming Language :: Python :: 3 :: Only
Classifier: License :: OSI Approved :: MIT License
Classifier: Topic :: Scientific/Engineering
Classifier: Intended Audience :: Science/Research
Classifier: Intended Audience :: Developers
Requires-Python: >=3.6
Requires-Dist: jsonargparse (>=2.32.2)
Requires-Dist: jsonschema (>=3.2.0)
Requires-Dist: numpy (>=1.18.5)
Requires-Dist: scipy (>=1.5.0)
Requires-Dist: pandas (>=1.0.1)
Requires-Dist: matplotlib (>=3.1.3)
Requires-Dist: xarray (>=0.16.0)
Requires-Dist: arviz (>=0.9.0)
Provides-Extra: dev
Requires-Dist: pystan (>=2.19.1.1) ; extra == 'dev'
Requires-Dist: pymc3 (>=3.9.0) ; extra == 'dev'
Requires-Dist: pyro-ppl (>=0.4.1) ; extra == 'dev'
Requires-Dist: numpyro (>=0.3.0) ; extra == 'dev'
Requires-Dist: black (==20.8b1) ; extra == 'dev'
Requires-Dist: isort ; extra == 'dev'
Requires-Dist: flake8 ; extra == 'dev'
Requires-Dist: mypy ; extra == 'dev'
Provides-Extra: ppls
Requires-Dist: pystan (>=2.19.1.1) ; extra == 'ppls'
Requires-Dist: pymc3 (>=3.9.0) ; extra == 'ppls'
Requires-Dist: pyro-ppl (>=0.4.1) ; extra == 'ppls'
Requires-Dist: numpyro (>=0.3.0) ; extra == 'ppls'
